lookoutvision/__init__.py
lookoutvision/image.py
lookoutvision/lookoutvision.py
lookoutvision/manifest.py
lookoutvision/metrics.py
lookoutvision-0.1.10.dist-info/LICENSE
lookoutvision-0.1.10.dist-info/METADATA
lookoutvision-0.1.10.dist-info/NOTICE
lookoutvision-0.1.10.dist-info/WHEEL
lookoutvision-0.1.10.dist-info/top_level.txt
lookoutvision-0.1.10.dist-info/zip-safe
lookoutvision-0.1.10.dist-info/RECORD
