Metadata-Version: 2.1
Name: lookoutvision
Version: 0.1.10
Summary: Python SDK for Amazon Lookout for Vision
Home-page: UNKNOWN
Author: Michael Wallner
Author-email: wallnm@amazon.com
License: Apache-2.0
Platform: UNKNOWN
License-File: LICENSE
License-File: NOTICE
Requires-Dist: numpy
Requires-Dist: pandas
Requires-Dist: boto3
Requires-Dist: scikit-image
Requires-Dist: seaborn
Requires-Dist: matplotlib
